numath/__init__.py
numath/diferenciacion_numerica_e_integracion.py
numath/ecuaciones_una_variable.py
numath/transformacion.py
numath-0.0.4.dist-info/licenses/LICENSE
numath-0.0.4.dist-info/METADATA
numath-0.0.4.dist-info/WHEEL
numath-0.0.4.dist-info/top_level.txt
numath-0.0.4.dist-info/RECORD
