Metadata-Version: 2.4
Name: numath
Version: 0.0.4
Summary: Librería de operaciones matemáticas para Matemática Numérica
Home-page: https://github.com/rodri5villa/numath-Library
Author: Rodrigo Villa
Author-email: rodrigo.villa@alumnos.uneatlantico.es
License: MIT
Project-URL: Documentation, https://github.com/rodri5villa/numath-Library/tree/main/documentation/code
Project-URL: Issues, https://github.com/rodri5villa/numath-Library/issues
Classifier: Development Status :: 3 - Alpha
Classifier: Intended Audience :: Education
Classifier: Topic :: Scientific/Engineering :: Mathematics
Classifier: License :: OSI Approved :: MIT License
Classifier: Programming Language :: Python :: 3.11
Classifier: Operating System :: OS Independent
Requires-Python: >=3.10
License-File: LICENSE
Requires-Dist: numpy>=1.24
Provides-Extra: dev
Requires-Dist: pytest>=6.0; extra == "dev"
Provides-Extra: test
Requires-Dist: pytest; extra == "test"
Dynamic: author
Dynamic: author-email
Dynamic: classifier
Dynamic: description
Dynamic: description-content-type
Dynamic: home-page
Dynamic: license
Dynamic: license-file
Dynamic: project-url
Dynamic: provides-extra
Dynamic: requires-dist
Dynamic: requires-python
Dynamic: summary
